basebolt/__init__.py
basebolt-0.0.1.dist-info/METADATA
basebolt-0.0.1.dist-info/WHEEL
basebolt-0.0.1.dist-info/top_level.txt
basebolt-0.0.1.dist-info/RECORD
