Metadata-Version: 2.1
Name: basebolt
Version: 0.0.1
Summary: SDK for the BaseBolt API
Author-email: Taylor AI <contact@trytaylor.ai>
Classifier: Programming Language :: Python :: 3
Classifier: License :: OSI Approved :: MIT License
Classifier: Operating System :: OS Independent
Requires-Python: >=3.9
